README.rst
setup.py
pijnu/__init__.py
pijnu.egg-info/PKG-INFO
pijnu.egg-info/SOURCES.txt
pijnu.egg-info/dependency_links.txt
pijnu.egg-info/pbr.json
pijnu.egg-info/requires.txt
pijnu.egg-info/top_level.txt
pijnu/generator/None.py
pijnu/generator/__init__.py
pijnu/generator/genTest.py
pijnu/generator/genTestParser.py
pijnu/generator/generator.py
pijnu/generator/pijnuActions.py
pijnu/generator/pijnuParser.py
pijnu/library/__init__.py
pijnu/library/charset.py
pijnu/library/error.py
pijnu/library/gParser.py
pijnu/library/node.py
pijnu/library/parser.py
pijnu/library/pattern.py
pijnu/library/preprocess.py
pijnu/library/testError.py
pijnu/library/testParserParser.py
pijnu/library/testPattern.py
pijnu/library/testValidParser.py
pijnu/library/testing.py
pijnu/library/tools.py